ebiose_cloud_client/__init__.py
ebiose_cloud_client/api_client.py
ebiose_cloud_client/api_response.py
ebiose_cloud_client/configuration.py
ebiose_cloud_client/exceptions.py
ebiose_cloud_client/py.typed
ebiose_cloud_client/rest.py
ebiose_cloud_client/api/__init__.py
ebiose_cloud_client/api/api_key_api.py
ebiose_cloud_client/api/auth_endpoints_api.py
ebiose_cloud_client/api/backend_api.py
ebiose_cloud_client/api/ecosystem_endpoints_api.py
ebiose_cloud_client/api/forge_endpoints_api.py
ebiose_cloud_client/api/front_api_api.py
ebiose_cloud_client/api/users_api.py
ebiose_cloud_client/models/__init__.py
ebiose_cloud_client/models/agent_input_model.py
ebiose_cloud_client/models/agent_model_input_model.py
ebiose_cloud_client/models/agent_model_output_model.py
ebiose_cloud_client/models/agent_model_type.py
ebiose_cloud_client/models/agent_output_model.py
ebiose_cloud_client/models/agent_type.py
ebiose_cloud_client/models/api_key_input_model.py
ebiose_cloud_client/models/api_key_output_model.py
ebiose_cloud_client/models/ecosystem_input_model.py
ebiose_cloud_client/models/ecosystem_output_model.py
ebiose_cloud_client/models/forge_cycle_input_model.py
ebiose_cloud_client/models/forge_cycle_output_model.py
ebiose_cloud_client/models/forge_cycle_status.py
ebiose_cloud_client/models/forge_input_model.py
ebiose_cloud_client/models/forge_output_model.py
ebiose_cloud_client/models/front_api_agent_details_output_model.py
ebiose_cloud_client/models/front_api_agent_output_model.py
ebiose_cloud_client/models/login_input_model.py
ebiose_cloud_client/models/login_output_model.py
ebiose_cloud_client/models/new_cycle_output_model.py
ebiose_cloud_client/models/node_model.py
ebiose_cloud_client/models/node_type.py
ebiose_cloud_client/models/role.py
ebiose_cloud_client/models/self_api_key_input_model.py
ebiose_cloud_client/models/self_user_input_model.py
ebiose_cloud_client/models/signup_input_model.py
ebiose_cloud_client/models/start_forge_cycle_input_model.py
ebiose_cloud_client-0.1.137.dist-info/METADATA
ebiose_cloud_client-0.1.137.dist-info/WHEEL
ebiose_cloud_client-0.1.137.dist-info/top_level.txt
ebiose_cloud_client-0.1.137.dist-info/RECORD
